gitpulse/__init__.py
gitpulse/badges.py
gitpulse/cache.py
gitpulse/cli.py
gitpulse/github_api.py
gitpulse/models.py
gh_pulse-0.1.0.dist-info/METADATA
gh_pulse-0.1.0.dist-info/WHEEL
gh_pulse-0.1.0.dist-info/entry_points.txt
gh_pulse-0.1.0.dist-info/licenses/LICENSE
gh_pulse-0.1.0.dist-info/RECORD
