Metadata-Version: 2.4
Name: gh-pulse
Version: 0.1.0
Summary: GitHub productivity CLI - analyze repos, generate badges, and automate README updates
Project-URL: Homepage, https://github.com/ruslanlap/gitpulse
Project-URL: Repository, https://github.com/ruslanlap/gitpulse
Project-URL: Issues, https://github.com/ruslanlap/gitpulse/issues
Author-email: Ruslan <ruslan@example.com>
License: MIT
License-File: LICENSE
Keywords: analytics,badges,cli,github,productivity
Classifier: Development Status :: 3 - Alpha
Classifier: Intended Audience :: Developers
Classifier: License :: OSI Approved :: MIT License
Classifier: Programming Language :: Python :: 3
Classifier: Programming Language :: Python :: 3.11
Classifier: Programming Language :: Python :: 3.12
Requires-Python: >=3.11
Requires-Dist: httpx>=0.27.0
Requires-Dist: keyring>=25.0.0
Requires-Dist: pydantic>=2.6.0
Requires-Dist: rich>=13.7.0
Requires-Dist: typer[all]>=0.12.0
Provides-Extra: dev
Requires-Dist: pytest-asyncio>=0.23.0; extra == 'dev'
Requires-Dist: pytest-cov>=4.1.0; extra == 'dev'
Requires-Dist: pytest>=8.0.0; extra == 'dev'
Requires-Dist: ruff>=0.3.0; extra == 'dev'
